collective.volto.dropdownmenu-1.3.2-py3.11-nspkg.pth
collective/volto/dropdownmenu/__init__.py
collective/volto/dropdownmenu/configure.zcml
collective/volto/dropdownmenu/interfaces.py
collective/volto/dropdownmenu/permissions.zcml
collective/volto/dropdownmenu/setuphandlers.py
collective/volto/dropdownmenu/testing.py
collective/volto/dropdownmenu/upgrades.py
collective/volto/dropdownmenu/upgrades.zcml
collective/volto/dropdownmenu/browser/__init__.py
collective/volto/dropdownmenu/browser/configure.zcml
collective/volto/dropdownmenu/browser/controlpanel.py
collective/volto/dropdownmenu/locales/README.rst
collective/volto/dropdownmenu/locales/__init__.py
collective/volto/dropdownmenu/locales/collective.volto.dropdownmenu.pot
collective/volto/dropdownmenu/locales/update.py
collective/volto/dropdownmenu/locales/update.sh
collective/volto/dropdownmenu/locales/es/LC_MESSAGES/collective.volto.dropdownmenu.po
collective/volto/dropdownmenu/locales/it/LC_MESSAGES/collective.volto.dropdownmenu.po
collective/volto/dropdownmenu/profiles/default/browserlayer.xml
collective/volto/dropdownmenu/profiles/default/controlpanel.xml
collective/volto/dropdownmenu/profiles/default/metadata.xml
collective/volto/dropdownmenu/profiles/default/registry.xml
collective/volto/dropdownmenu/profiles/default/rolemap.xml
collective/volto/dropdownmenu/profiles/uninstall/browserlayer.xml
collective/volto/dropdownmenu/profiles/uninstall/controlpanel.xml
collective/volto/dropdownmenu/profiles/uninstall/registry.xml
collective/volto/dropdownmenu/restapi/__init__.py
collective/volto/dropdownmenu/restapi/configure.zcml
collective/volto/dropdownmenu/restapi/deserializer/__init__.py
collective/volto/dropdownmenu/restapi/deserializer/configure.zcml
collective/volto/dropdownmenu/restapi/deserializer/dropdown_menu.py
collective/volto/dropdownmenu/restapi/dropdown_menu/__init__.py
collective/volto/dropdownmenu/restapi/dropdown_menu/configure.zcml
collective/volto/dropdownmenu/restapi/dropdown_menu/get.py
collective.volto.dropdownmenu-1.3.2.dist-info/LICENSE.GPL
collective.volto.dropdownmenu-1.3.2.dist-info/LICENSE.rst
collective.volto.dropdownmenu-1.3.2.dist-info/METADATA
collective.volto.dropdownmenu-1.3.2.dist-info/WHEEL
collective.volto.dropdownmenu-1.3.2.dist-info/entry_points.txt
collective.volto.dropdownmenu-1.3.2.dist-info/namespace_packages.txt
collective.volto.dropdownmenu-1.3.2.dist-info/top_level.txt
collective.volto.dropdownmenu-1.3.2.dist-info/RECORD
