Metadata-Version: 2.1
Name: collective.volto.dropdownmenu
Version: 1.3.2
Summary: Add-on for Volto to manage a dropdown menu.
Home-page: https://github.com/collective/collective.volto.dropdownmenu
Author: RedTurtle Technology
Author-email: sviluppo@redturtle.it
License: GPL version 2
Project-URL: PyPI, https://pypi.python.org/pypi/collective.volto.dropdownmenu
Project-URL: Source, https://github.com/collective/collective.volto.dropdownmenu
Project-URL: Tracker, https://github.com/collective/collective.volto.dropdownmenu/issues
Keywords: Python Plone Volto
Classifier: Environment :: Web Environment
Classifier: Framework :: Plone
Classifier: Framework :: Plone :: Addon
Classifier: Framework :: Plone :: 5.2
Classifier: Programming Language :: Python
Classifier: Programming Language :: Python :: 3.6
Classifier: Programming Language :: Python :: 3.7
Classifier: Operating System :: OS Independent
Classifier: License :: OSI Approved :: GNU General Public License v2 (GPLv2)
Requires-Python: >=3.7
License-File: LICENSE.GPL
License-File: LICENSE.rst
Requires-Dist: setuptools
Requires-Dist: plone.api>=1.8.4
Requires-Dist: plone.restapi
Provides-Extra: test
Requires-Dist: plone.app.testing; extra == "test"
Requires-Dist: plone.testing>=5.0.0; extra == "test"
Requires-Dist: plone.app.contenttypes; extra == "test"
Requires-Dist: plone.app.robotframework[debug]; extra == "test"
Requires-Dist: collective.MockMailHost; extra == "test"
